{
  "kind": "collectionType",
  "collectionName": "contact_submissions",
  "info": {
    "singularName": "contact-submission",
    "pluralName": "contact-submissions",
    "displayName": "Contact Submission",
    "description": "Leads submitted via the website contact form"
  },
  "options": {
    "draftAndPublish": false
  },
  "pluginOptions": {},
  "attributes": {
    "firstName": {
      "type": "string",
      "required": true
    },
    "lastName": {
      "type": "string",
      "required": true
    },
    "email": {
      "type": "email",
      "required": true
    },
    "phone": {
      "type": "string"
    },
    "jobTitle": {
      "type": "string"
    },
    "company": {
      "type": "string"
    },
    "country": {
      "type": "string"
    },
    "message": {
      "type": "text"
    },
    "marketingOptIn": {
      "type": "boolean",
      "default": false
    },
    "timeToSubmitMs": {
      "type": "integer"
    }
  }
}
